icekit_notifications-0.2.1.dist-info/DESCRIPTION.rst
icekit_notifications-0.2.1.dist-info/METADATA
icekit_notifications-0.2.1.dist-info/RECORD
icekit_notifications-0.2.1.dist-info/WHEEL
icekit_notifications-0.2.1.dist-info/metadata.json
icekit_notifications-0.2.1.dist-info/top_level.txt
notifications/__init__.py
notifications/admin.py
notifications/apps.py
notifications/appsettings.py
notifications/models.py
notifications/notifier.py
notifications/signals.py
notifications/migrations/0001_initial.py
notifications/migrations/0002_auto_20150901_2126.py
notifications/migrations/__init__.py
notifications/templates/notifications/mail/base.html
notifications/tests/__init__.py
notifications/tests/admin.py
notifications/tests/models.py
notifications/tests/settings.py
notifications/tests/settings_postgres.py
notifications/tests/tests.py
notifications/tests/urls.py
notifications/utils/__init__.py
notifications/utils/creation.py
