Metadata-Version: 2.0
Name: icekit-notifications
Version: 0.2.1
Summary: UNKNOWN
Home-page: https://github.com/ixc/icekit-notifications
Author: Interaction Consortium
Author-email: studio@interaction.net.au
License: MIT
Platform: UNKNOWN
Requires-Dist: WebTest
Requires-Dist: coverage
Requires-Dist: django-dynamic-fixture
Requires-Dist: django-model-utils
Requires-Dist: django-nose
Requires-Dist: django-polymorphic
Requires-Dist: django-webtest
Requires-Dist: mkdocs
Requires-Dist: nose-progressive
Provides-Extra: dev
Requires-Dist: ipdb; extra == 'dev'
Requires-Dist: ipython; extra == 'dev'
Provides-Extra: postgres
Requires-Dist: psycopg2; extra == 'postgres'
Provides-Extra: testing
Requires-Dist: mock; extra == 'testing'
Requires-Dist: requests; extra == 'testing'
